tsetmc_pusher/__init__.py
tsetmc_pusher/client.py
tsetmc_pusher/timing.py
tsetmc_pusher/server/__init__.py
tsetmc_pusher/server/operation.py
tsetmc_pusher/server/repository.py
tsetmc_pusher/server/websocket.py
tsetmc_pusher-1.1.3.dist-info/METADATA
tsetmc_pusher-1.1.3.dist-info/WHEEL
tsetmc_pusher-1.1.3.dist-info/top_level.txt
tsetmc_pusher-1.1.3.dist-info/RECORD
