Metadata-Version: 2.1
Name: tsetmc-pusher
Version: 1.1.3
Summary: Pusher for Tehran Stock Exchange data crawled from TSETMC website.
Author: Arka Equities & Securities
Author-email: zare@arkaequities.com
Classifier: Programming Language :: Python :: 3
Classifier: Operating System :: POSIX :: Linux
Classifier: Operating System :: MacOS :: MacOS X
Classifier: Operating System :: Microsoft :: Windows
Requires-Dist: httpx
Requires-Dist: websockets
Requires-Dist: python-dotenv
Requires-Dist: tse-utils
